factorio_randovania_mod/__init__.py
factorio_randovania_mod/__main__.py
factorio_randovania_mod/cli.py
factorio_randovania_mod/configuration.pyi
factorio_randovania_mod/factorio_formats.py
factorio_randovania_mod/layout_data.py
factorio_randovania_mod/layout_string.py
factorio_randovania_mod/locale_lib.py
factorio_randovania_mod/lua_util.py
factorio_randovania_mod/mod_lua_api.py
factorio_randovania_mod/mod_zip.py
factorio_randovania_mod/py.typed
factorio_randovania_mod/schema.py
factorio_randovania_mod/validator_with_default.py
factorio_randovania_mod/version.py
factorio_randovania_mod/__pyinstaller/__init__.py
factorio_randovania_mod/__pyinstaller/hook-factorio_randovania_mod.py
factorio_randovania_mod/files/schema.json
factorio_randovania_mod/lua_src/control.lua
factorio_randovania_mod/lua_src/data-updates.lua
factorio_randovania_mod/lua_src/data.lua
factorio_randovania_mod/lua_src/info.json
factorio_randovania_mod/lua_src/layout.lua
factorio_randovania_mod/lua_src/settings.lua
factorio_randovania_mod/lua_src/thumbnail.png
factorio_randovania_mod/lua_src/external_libs/Blob.lua
factorio_randovania_mod/lua_src/external_libs/Blob.meta.lua
factorio_randovania_mod/lua_src/external_libs/LibDeflate.lua
factorio_randovania_mod/lua_src/external_libs/base64.lua
factorio_randovania_mod/lua_src/locale/en/strings.cfg
factorio_randovania_mod/lua_src/prototypes/burners.lua
factorio_randovania_mod/lua_src/prototypes/extra-tiers.lua
factorio_randovania_mod/lua_src/prototypes/handcraft.lua
factorio_randovania_mod/lua_src/prototypes/modules.lua
factorio_randovania_mod/lua_src/prototypes/tech.lua
factorio_randovania_mod-0.8.1.dist-info/licenses/LICENSE
factorio_randovania_mod-0.8.1.dist-info/METADATA
factorio_randovania_mod-0.8.1.dist-info/WHEEL
factorio_randovania_mod-0.8.1.dist-info/entry_points.txt
factorio_randovania_mod-0.8.1.dist-info/top_level.txt
factorio_randovania_mod-0.8.1.dist-info/RECORD
