Metadata-Version: 2.4
Name: factorio-randovania-mod
Version: 0.8.1
Summary: Generator of Factorio Randomizer mods for Randovania
Author: Henrique Gemignani Passos Lima
Project-URL: Homepage, https://github.com/randovania/factorio-randovania-mod
Classifier: License :: OSI Approved :: GNU General Public License v3 (GPLv3)
Classifier: Development Status :: 3 - Alpha
Classifier: Intended Audience :: Developers
Classifier: Programming Language :: Python :: 3.11
Classifier: Programming Language :: Python :: 3.12
Classifier: Programming Language :: Python :: 3.13
Requires-Python: >=3.11
License-File: LICENSE
Requires-Dist: jsonschema
Requires-Dist: construct
Provides-Extra: test
Requires-Dist: pytest; extra == "test"
Requires-Dist: pytest-cov; extra == "test"
Requires-Dist: pytest-mock; extra == "test"
Requires-Dist: pre-commit; extra == "test"
Provides-Extra: typing
Requires-Dist: mypy; extra == "typing"
Requires-Dist: types-Pillow; extra == "typing"
Requires-Dist: types-pyinstaller; extra == "typing"
Requires-Dist: types-jsonschema; extra == "typing"
Dynamic: license-file
